pymediainfo_cli/__init__.py
pymediainfo_cli/__main__.py
pymediainfo_cli/main.py
pymediainfo_cli-0.2.1.dist-info/LICENSE.md
pymediainfo_cli-0.2.1.dist-info/METADATA
pymediainfo_cli-0.2.1.dist-info/WHEEL
pymediainfo_cli-0.2.1.dist-info/entry_points.txt
pymediainfo_cli-0.2.1.dist-info/RECORD
