Metadata-Version: 2.1
Name: pymediainfo-cli
Version: 0.2.1
Summary: CLI version of the pymediainfo package
Home-page: https://github.com/GuiEpi/pymediainfo-cli
License: MIT
Keywords: cli,mediainfo
Author: Guillaume Coussot
Author-email: guillaume.coussot@gmail.com
Requires-Python: >=3.11,<4.0
Classifier: License :: OSI Approved :: MIT License
Classifier: Programming Language :: Python :: 3
Classifier: Programming Language :: Python :: 3.11
Classifier: Programming Language :: Python :: 3.12
Requires-Dist: pymediainfo (>=6.1.0,<7.0.0)
Requires-Dist: typer[all] (>=0.9.0,<0.10.0)
Project-URL: Repository, https://github.com/GuiEpi/pymediainfo-cli
